bgstools/__init__.py
bgstools/datastorage/__init__.py
bgstools/datastorage/datastorage.py
bgstools/experimental/__init__.py
bgstools/experimental/lambdas.py
bgstools/io/__init__.py
bgstools/io/io.py
bgstools/io/media.py
bgstools/requirements.txt
bgstools/spatial/__init__.py
bgstools/spatial/spatial.py
bgstools/stt/__init__.py
bgstools/stt/stt.py
bgstools/utils/__init__.py
bgstools/utils/utils.py
bgstools/version.py
bgstools-0.2.2.dist-info/METADATA
bgstools-0.2.2.dist-info/WHEEL
bgstools-0.2.2.dist-info/RECORD
