Metadata-Version: 2.1
Name: bgstools
Version: 0.2.2
Summary: BeGeoSpatial Development Tools
Author: José Beltrán
Author-email: 102664984+jose-begeospatial@users.noreply.github.com
Requires-Python: >=3.11,<4.0
Classifier: Programming Language :: Python :: 3
Classifier: Programming Language :: Python :: 3.11
Classifier: Programming Language :: Python :: 3.12
Requires-Dist: PyYAML (>=6.0,<7.0)
Requires-Dist: certifi (>=2023.5.7,<2024.0.0)
Requires-Dist: h3 (>=3.7.6,<4.0.0)
Requires-Dist: opencv-python (>=4.7.0.72,<5.0.0.0)
Requires-Dist: pyproj (>=3.5.0,<4.0.0)
Requires-Dist: streamlit (>=1.28.2,<2.0.0)
